canopy/__init__.py
canopy/static/enliven.js
canopy/static/fleuron-dingbats.woff
canopy/static/fleuron-dingbats.woff2
canopy/static/fleuron-mixed.woff
canopy/static/fleuron-mixed.woff2
canopy/static/fleuron-regular.woff
canopy/static/fleuron-regular.woff2
canopy/static/recognizer-processor.js
canopy/static/screen.css
canopy/static/ubuntu-bold-italic.ttf
canopy/static/ubuntu-bold.ttf
canopy/static/ubuntu-light-italic.ttf
canopy/static/ubuntu-light.ttf
canopy/static/ubuntu-medium-italic.ttf
canopy/static/ubuntu-medium.ttf
canopy/static/ubuntu-regular-italic.ttf
canopy/static/ubuntu-regular.ttf
canopy/templates/__init__.py
canopy/templates/guide.html
canopy/templates/index.html
canopy/templates/template.html
canopy_platform-0.0.105.dist-info/METADATA
canopy_platform-0.0.105.dist-info/entry_points.txt
canopy_platform-0.0.105.dist-info/WHEEL
canopy_platform-0.0.105.dist-info/RECORD
